[{"id":"rv_ch_01fnydb1qkc5gbjd3eg01d2jen","first_name":"Linh","last_name":"Legros","email":"linh@wehner-bruen.net","organization":"Hahn, Balistreri and Hettinger","amount":1693,"created_at":1638465780,"address":"8448 Allan Path","city":"Jastmouth","state":"NY","postal_code":"64229-0835","subscription":"true","account_type":"non-user"},{"id":"rv_ch_01fnydb1qncxphem2xkrgzdswz","first_name":"Shan","last_name":"Romaguera","email":"shan@pacocha.io","organization":"Volkman and Sons","amount":4440,"created_at":1638405771,"address":"758 Kellee Fall","city":"Calandratown","state":"VA","postal_code":"07316","subscription":"false","account_type":"user"},{"id":"rv_ch_01fnydb1r7qm87dnfk1efxmxxf","first_name":"Marcus","last_name":"Mitchell","email":"marcus@ferry.biz","organization":"Kreiger Group","amount":3290,"created_at":1638456139,"address":"5429 Hegmann Neck","city":"New Dwainburgh","state":"ME","postal_code":"99941-5135","subscription":"true","account_type":"user"},{"id":"rv_ch_01fnydb1r9vy8eeegr0e2ggyyh","first_name":"Tamisha","last_name":"Bailey","email":"tamisha@flatley-hettinger.org","organization":"Runte-Batz","amount":9187,"created_at":1638419645,"address":"79618 Clarice Crossroad","city":"Farrellfort","state":"CA","postal_code":"74256-5063","subscription":"true","account_type":"non-user"},{"id":"rv_ch_01fnydb1t4jzrvcgmsce12m9ng","first_name":"Debra","last_name":"Schaden","email":"debra@altenwerth.name","organization":"Thiel and Sons","amount":4286,"created_at":1638414758,"address":"1504 Florida Extension","city":"New Kathlyn","state":"CA","postal_code":"84306","subscription":"true","account_type":"user"},{"id":"rv_ch_01fnydb1t5q9fhw7gvghvt96qf","first_name":"Rod","last_name":"Botsford","email":"rod@quigley.co","organization":"Pfeffer, Jakubowski and Jacobs","amount":6117,"created_at":1638466178,"address":"708 Gleason Summit","city":"North Timmymouth","state":"AK","postal_code":"64388-9782","subscription":"true","account_type":"non-user"},{"id":"rv_ch_01fnydb1w0nkvgyhbpfhs0hr71","first_name":"Collette","last_name":"Bednar","email":"collette@dickinson.com","organization":"Krajcik-Emard","amount":6164,"created_at":1638443768,"address":"78563 Block Harbors","city":"Hansenshire","state":"UT","postal_code":"41350","subscription":"false","account_type":"user"},{"id":"rv_ch_01fnydb1w1b846j8ksrb9dywhc","first_name":"Selena","last_name":"Larson","email":"selena@schmeler-torp.org","organization":"Gerhold, Mertz and Rosenbaum","amount":1100,"created_at":1638464905,"address":"90153 Kellye Junction","city":"Nathanton","state":"OR","postal_code":"20326-2305","subscription":"true","account_type":"non-user"},{"id":"rv_ch_01fnydb1xw19k96a8ez62k9a0e","first_name":"Merrill","last_name":"Mertz","email":"merrill@runolfsdottir.info","organization":"MacGyver-D'Amore","amount":6951,"created_at":1638471941,"address":"181 Gene Forest","city":"Lake Alejandro","state":"KY","postal_code":"56585","subscription":"false","account_type":"user"},{"id":"rv_ch_01fnydb1xyty6ys824xwwzaqx0","first_name":"Veronica","last_name":"Hermann","email":"veronica@russel-thiel.biz","organization":"Hyatt-Wolf","amount":7280,"created_at":1638394839,"address":"264 Annelle Ville","city":"New Medafurt","state":"AR","postal_code":"31269","subscription":"false","account_type":"non-user"},{"id":"rv_ch_01fnydb1z4q4ecwc4j8cpck28f","first_name":"Mario","last_name":"Kohler","email":"mario@gutkowski.org","organization":"Gerhold, Wuckert and Wunsch","amount":9577,"created_at":1638433164,"address":"65658 Miriam Street","city":"Prudenceside","state":"UT","postal_code":"68115","subscription":"true","account_type":"non-user"},{"id":"rv_ch_01fnydb20zj7z152vrp2b8f0pb","first_name":"Cortney","last_name":"Ward","email":"cortney@green-ebert.io","organization":"Balistreri Group","amount":2577,"created_at":1638440682,"address":"582 Quinn Stream","city":"Mannview","state":"MA","postal_code":"04923","subscription":"true","account_type":"user"},{"id":"rv_ch_01fnydb211hgg8xyfdh39x7y8x","first_name":"Silas","last_name":"VonRueden","email":"silas@batz.com","organization":"Lang and Sons","amount":2986,"created_at":1638433214,"address":"7106 Nikolaus Keys","city":"South Dellaland","state":"OH","postal_code":"31148-2713","subscription":"false","account_type":"non-user"},{"id":"rv_ch_01fnydb22txaxex3kcyferd76f","first_name":"Tyler","last_name":"Gerlach","email":"tyler@hahn.co","organization":"Hilll Group","amount":3703,"created_at":1638476591,"address":"4645 Lowe Centers","city":"Thaoside","state":"NV","postal_code":"90365","subscription":"true","account_type":"non-user"},{"id":"rv_ch_01fnydb22wkrthh189vp8gr8fj","first_name":"Rebbecca","last_name":"Baumbach","email":"rebbecca@dare.net","organization":"Herman, Swaniawski and Beatty","amount":8190,"created_at":1638469329,"address":"44542 Madelyn Drives","city":"Lake Gordonport","state":"FL","postal_code":"68596","subscription":"true","account_type":"non-user"},{"id":"rv_ch_01fnydb24pxxz8m3w8ax467be1","first_name":"Trey","last_name":"Bashirian","email":"trey@jones.name","organization":"Stehr, Kling and Miller","amount":2204,"created_at":1638426737,"address":"422 Aubrey Mews","city":"Cartershire","state":"AK","postal_code":"83662-6679","subscription":"false","account_type":"user"},{"id":"rv_ch_01fnydb24rb6pt64byk9a8mdf7","first_name":"Keena","last_name":"Weber","email":"keena@grady.net","organization":"Parisian-Bogisich","amount":9366,"created_at":1638424586,"address":"37910 Emmanuel Crossing","city":"North Colemanport","state":"RI","postal_code":"24295-9302","subscription":"true","account_type":"user"},{"id":"rv_ch_01fnydb25yfmh5dmpa86wpedzf","first_name":"Claudio","last_name":"Rogahn","email":"claudio@deckow.info","organization":"Stracke and Sons","amount":9360,"created_at":1638392764,"address":"5898 Halvorson Junction","city":"Ezrafort","state":"RI","postal_code":"74330","subscription":"true","account_type":"user"},{"id":"rv_ch_01fnydb260ah2gz91tmbsa6qmn","first_name":"Garth","last_name":"O'Conner","email":"garth@hackett.info","organization":"Gerlach Group","amount":4198,"created_at":1638433339,"address":"83151 Mila Coves","city":"East Cristina","state":"IL","postal_code":"36494","subscription":"false","account_type":"user"},{"id":"rv_ch_01fnydb261rfv9gep93bqefj7s","first_name":"Yun","last_name":"Green","email":"yun@casper.com","organization":"Smith-Kozey","amount":3490,"created_at":1638431073,"address":"3383 Deandra Ports","city":"West Tegan","state":"NC","postal_code":"58612-9265","subscription":"true","account_type":"user"},{"id":"rv_ch_01fnydb27vafjkjwgzx1avzygf","first_name":"Hassan","last_name":"Welch","email":"hassan@osinski-maggio.net","organization":"Gusikowski, Conroy and O'Hara","amount":2142,"created_at":1638426638,"address":"47974 Israel Rue","city":"Antonychester","state":"WI","postal_code":"39669","subscription":"false","account_type":"user"},{"id":"rv_ch_01fnydb27xznszdqmdfq3gepz0","first_name":"Talia","last_name":"Dare","email":"talia@wehner.co","organization":"Schuppe-Gleason","amount":9209,"created_at":1638403165,"address":"782 Runolfsson Club","city":"Boyleborough","state":"OK","postal_code":"40027-1720","subscription":"true","account_type":"user"},{"id":"rv_ch_01fnydb29qm6c6etxpmh362rb6","first_name":"Bobby","last_name":"Lang","email":"bobby@jerde.info","organization":"Kling LLC","amount":8431,"created_at":1638408437,"address":"1975 Russel Squares","city":"New Bretport","state":"ID","postal_code":"92227-9375","subscription":"false","account_type":"user"},{"id":"rv_ch_01fnydb29st803hv962wxrag71","first_name":"Leonore","last_name":"Little","email":"leonore@stoltenberg.net","organization":"Zemlak Inc","amount":9719,"created_at":1638407315,"address":"6271 Altenwerth Ridge","city":"Aundreashire","state":"NJ","postal_code":"08989-0912","subscription":"false","account_type":"user"},{"id":"rv_ch_01fnydb2bk4rzxj69m4jnpangq","first_name":"Coleman","last_name":"Reilly","email":"coleman@abernathy-mante.org","organization":"Durgan Group","amount":4766,"created_at":1638467909,"address":"85172 Valentine Flat","city":"New Angelyn","state":"HI","postal_code":"97081","subscription":"true","account_type":"non-user"},{"id":"rv_ch_01fnydb2bnxntpjnbrbf7mfgbh","first_name":"Hipolito","last_name":"Muller","email":"hipolito@rodriguez.com","organization":"Waters-Runte","amount":8022,"created_at":1638435938,"address":"22217 Dickens Harbor","city":"New Grantmouth","state":"OK","postal_code":"21257","subscription":"true","account_type":"user"},{"id":"rv_ch_01fnydb2ct7m7pgp1nf9snap50","first_name":"Bryant","last_name":"Mraz","email":"bryant@cassin.com","organization":"Lubowitz Group","amount":9977,"created_at":1638445270,"address":"698 Champlin Stravenue","city":"South Tylerside","state":"NC","postal_code":"65192","subscription":"true","account_type":"non-user"},{"id":"rv_ch_01fnydb2cwjmt27jdvaqj8khcy","first_name":"Zenaida","last_name":"Morissette","email":"zenaida@corwin.com","organization":"Cartwright, Gleason and Dickens","amount":4045,"created_at":1638441137,"address":"99216 Cormier Hill","city":"East Fabiola","state":"IA","postal_code":"21713","subscription":"false","account_type":"non-user"},{"id":"rv_ch_01fnydb2ep968dmamjma9sdar0","first_name":"Loris","last_name":"Ernser","email":"loris@keeling-schumm.io","organization":"Osinski Group","amount":5261,"created_at":1638434724,"address":"9509 Maurice Glen","city":"New Doyle","state":"KS","postal_code":"66359","subscription":"true","account_type":"non-user"},{"id":"rv_ch_01fnydb2erccnvqdcbn2epxsaz","first_name":"Booker","last_name":"Corkery","email":"booker@roob.name","organization":"Fisher Group","amount":9173,"created_at":1638455916,"address":"161 Len Road","city":"New Tillie","state":"NJ","postal_code":"94209-3437","subscription":"true","account_type":"non-user"}]